<?xml version="1.0" encoding="UTF-8"?>
<con:resource name="/glrestapi/rest/v1/gldocument/{Vuuid}" path="/glrestapi/rest/v1/gldocument/{Vuuid}" id="497794eb-64e9-48c9-9f2c-4b3188fbd0cd" xmlns:con="http://eviware.com/soapui/config">
  <con:settings>
    <con:setting id="497794eb-64e9-48c9-9f2c-4b3188fbd0cdfileName">%2Fglrestapi%2Frest%2Fv1%2Fgldocument%2F%7BVuuid%7D</con:setting>
  </con:settings>
  <con:parameters/>
  <con:method name="GET" id="de2e6306-052c-4eeb-ae4d-1a930e6c761e" method="GET">
    <con:description>Retrieve a Specific GL document</con:description>
    <con:settings/>
    <con:parameters>
      <con:parameter required="true">
        <con:name>Vuuid</con:name>
        <con:style>TEMPLATE</con:style>
        <con:description>Unique Row ID</con:description>
      </con:parameter>
    </con:parameters>
    <con:representation type="RESPONSE">
      <con:mediaType>application/json</con:mediaType>
      <con:status>200</con:status>
      <con:params/>
      <con:description>Successful Operation</con:description>
      <con:sampleContent>{
  "DocCode" : "string",
  "DocName" : "string",
  "DocDesc" : "string",
  "DocCatCode" : "string",
  "DocCatName" : "string",
  "DocBudgtypeCode" : "string",
  "DocSeqtypeCode" : "string",
  "DocActionCode" : "string",
  "DocLstRunPer" : 0,
  "DocSuprDetCode" : "string",
  "DocSuprTtlCode" : "string",
  "DocTypeCode" : "string",
  "DocLstRunYr" : 0,
  "DocCompCode" : "string",
  "DocCon2Code" : "string",
  "DocDesc2" : "string",
  "DocDesc3" : "string",
  "DocDesc4" : "string",
  "DocUserCode" : "string",
  "DocConschartCode" : "string",
  "DocConschartName" : "string",
  "DocWidthNum" : 0,
  "DocLengthNum" : 0,
  "DocBalTableName" : "string",
  "DocBudgTableName" : "string",
  "DocAccTableName" : "string",
  "DocCurrCode" : "string",
  "DocFuncCode" : "string",
  "DocMaxPer" : 0,
  "DocPrvYr" : 0,
  "DocInterCompAccFlag" : "string",
  "DocCtrlAccFlag" : "string",
  "DocIuCreateDate" : "YYYY-MM-dd or YYYY-MM-ddTHH:mm:ss-ZZ:ZZ",
  "DocIuCreateUser" : "string",
  "DocIuUpdateDate" : "YYYY-MM-dd or YYYY-MM-ddTHH:mm:ss-ZZ:ZZ",
  "DocIuUpdateUser" : "string",
  "DiscriminatorCode" : "string",
  "DocVUuid" : "string"
}</con:sampleContent>
    </con:representation>
    <con:representation type="RESPONSE">
      <con:mediaType>application/json</con:mediaType>
      <con:status>400</con:status>
      <con:params/>
      <con:description>An error occurred while attempting to retrieve, create, or delete record(s)</con:description>
    </con:representation>
    <con:request name="Request 1" id="33480402-4e19-4842-b01c-ce8b48914be0" mediaType="application/json">
      <con:settings/>
      <con:endpoint>https://mobtest.cmiccloudr12.com/cmictestrti</con:endpoint>
      <con:parameters/>
    </con:request>
  </con:method>
  <con:method name="DELETE" id="883b2f41-0b65-4795-b8b3-811d36ebfc22" method="DELETE">
    <con:description>Delete a Specific GL document</con:description>
    <con:settings/>
    <con:parameters>
      <con:parameter required="true">
        <con:name>Vuuid</con:name>
        <con:style>TEMPLATE</con:style>
        <con:description>Unique Row ID</con:description>
      </con:parameter>
    </con:parameters>
    <con:representation type="RESPONSE">
      <con:mediaType>application/json</con:mediaType>
      <con:status>204</con:status>
      <con:params/>
      <con:description>Object has been successfully deleted.</con:description>
    </con:representation>
    <con:representation type="RESPONSE">
      <con:mediaType>application/json</con:mediaType>
      <con:status>400</con:status>
      <con:params/>
      <con:description>An error occurred while attempting to retrieve, create, or delete record(s)</con:description>
    </con:representation>
    <con:request name="Request 1" id="5859bac1-4717-4ea4-a20f-b0175afdab03" mediaType="application/json">
      <con:settings/>
      <con:endpoint>https://mobtest.cmiccloudr12.com/cmictestrti</con:endpoint>
      <con:parameters/>
    </con:request>
  </con:method>
  <con:method name="PATCH" id="495e7e93-b987-4d93-b3ca-f85f41a3344b" method="PATCH">
    <con:description>Update GL document</con:description>
    <con:settings/>
    <con:parameters>
      <con:parameter required="true">
        <con:name>Vuuid</con:name>
        <con:style>TEMPLATE</con:style>
        <con:description>Unique Row Id</con:description>
      </con:parameter>
    </con:parameters>
    <con:representation type="RESPONSE">
      <con:mediaType>application/json</con:mediaType>
      <con:status>200</con:status>
      <con:params/>
      <con:description>Successful Operation</con:description>
      <con:sampleContent>{
  "DocCode" : "string",
  "DocName" : "string",
  "DocDesc" : "string",
  "DocCatCode" : "string",
  "DocCatName" : "string",
  "DocBudgtypeCode" : "string",
  "DocSeqtypeCode" : "string",
  "DocActionCode" : "string",
  "DocLstRunPer" : 0,
  "DocSuprDetCode" : "string",
  "DocSuprTtlCode" : "string",
  "DocTypeCode" : "string",
  "DocLstRunYr" : 0,
  "DocCompCode" : "string",
  "DocCon2Code" : "string",
  "DocDesc2" : "string",
  "DocDesc3" : "string",
  "DocDesc4" : "string",
  "DocUserCode" : "string",
  "DocConschartCode" : "string",
  "DocConschartName" : "string",
  "DocWidthNum" : 0,
  "DocLengthNum" : 0,
  "DocBalTableName" : "string",
  "DocBudgTableName" : "string",
  "DocAccTableName" : "string",
  "DocCurrCode" : "string",
  "DocFuncCode" : "string",
  "DocMaxPer" : 0,
  "DocPrvYr" : 0,
  "DocInterCompAccFlag" : "string",
  "DocCtrlAccFlag" : "string",
  "DocIuCreateDate" : "YYYY-MM-dd or YYYY-MM-ddTHH:mm:ss-ZZ:ZZ",
  "DocIuCreateUser" : "string",
  "DocIuUpdateDate" : "YYYY-MM-dd or YYYY-MM-ddTHH:mm:ss-ZZ:ZZ",
  "DocIuUpdateUser" : "string",
  "DiscriminatorCode" : "string",
  "DocVUuid" : "string"
}</con:sampleContent>
    </con:representation>
    <con:representation type="RESPONSE">
      <con:mediaType>application/json</con:mediaType>
      <con:status>400</con:status>
      <con:params/>
      <con:description>An error occurred while attempting to retrieve, create, or delete record(s)</con:description>
    </con:representation>
    <con:representation type="REQUEST">
      <con:mediaType>application/vnd.oracle.adf.resourceitem+json</con:mediaType>
      <con:params/>
      <con:sampleContent>{"DocCode":"string","DocName":"string","DocCatCode":"string","DocSeqtypeCode":"string","DocConschartCode":"string","DocVUuid":"string"}</con:sampleContent>
    </con:representation>
    <con:request name="Request Example" id="2cf01891-69fc-4ce5-9911-7fb60a3080ea" mediaType="application/vnd.oracle.adf.resourceitem+json">
      <con:settings/>
      <con:endpoint>https://mobtest.cmiccloudr12.com/cmictestrti</con:endpoint>
      <con:request>{"DocCode":"string","DocName":"string","DocCatCode":"string","DocSeqtypeCode":"string","DocConschartCode":"string","DocVUuid":"string"}</con:request>
      <con:parameters/>
    </con:request>
  </con:method>
</con:resource>
