<?xml version="1.0" encoding="UTF-8"?>
<con:resource name="/ap-rest-api/rest/1/unpostedvouchers" path="/ap-rest-api/rest/1/unpostedvouchers" id="2a9f4844-43d0-4d5c-93a7-b497f8357329" xmlns:con="http://eviware.com/soapui/config" xmlns:xsi="http://www.w3.org/2001/XMLSchema-instance">
  <con:settings>
    <con:setting id="2a9f4844-43d0-4d5c-93a7-b497f8357329fileName">%2Fap-rest-api%2Frest%2F1%2Funpostedvouchers</con:setting>
  </con:settings>
  <con:parameters/>
  <con:method name="GET" id="9b615abc-163c-462c-b1c6-3d22555da32a" method="GET">
    <con:description>Retrieve Unposted Vouchers</con:description>
    <con:settings/>
    <con:parameters>
      <con:parameter>
        <con:name>finder</con:name>
        <con:value/>
        <con:style>QUERY</con:style>
        <con:default/>
        <con:description>UnpostedVoucherFinder</con:description>
      </con:parameter>
      <con:parameter>
        <con:name>WorkflowStatusVar</con:name>
        <con:value/>
        <con:style>QUERY</con:style>
        <con:default/>
        <con:description>Workflow Status (UnpostedVoucherFinder)</con:description>
      </con:parameter>
    </con:parameters>
    <con:representation type="RESPONSE">
      <con:mediaType>application/json</con:mediaType>
      <con:status>200</con:status>
      <con:params/>
      <con:description>Successful Operation</con:description>
      <con:sampleContent>{
  "VouNum" : 0,
  "VouBchNum" : 0,
  "VouCompCode" : "string",
  "VouTranCode" : "string",
  "VouVenCode" : "string",
  "VouDeptCode" : "string",
  "VouCashAccCode" : "string",
  "VouInvCode" : "string",
  "VouDueDate" : "YYYY-MM-dd or YYYY-MM-ddTHH:mm:ss-ZZ:ZZ",
  "VouDiscDate" : "YYYY-MM-dd or YYYY-MM-ddTHH:mm:ss-ZZ:ZZ",
  "VouPoNum" : "string",
  "VouContCode" : "string",
  "VouChgCode" : "string",
  "VouJobCode" : "string",
  "VouInvDate" : "YYYY-MM-dd or YYYY-MM-ddTHH:mm:ss-ZZ:ZZ",
  "VouTax1Code" : "string",
  "VouTax2Code" : "string",
  "VouGsthldbkCode" : "string",
  "VouTaxDiscCode" : "string",
  "VouTax2DiscCode" : "string",
  "VouFrtDiscCode" : "string",
  "VouMiscDiscCode" : "string",
  "VouDesc1" : "string",
  "VouDesc2" : "string",
  "VouStatusCode" : "string",
  "VouPayCode" : "string",
  "VouCurrCode" : "string",
  "VouPostDate" : "YYYY-MM-dd or YYYY-MM-ddTHH:mm:ss-ZZ:ZZ",
  "VouPoPrtCode" : "string",
  "VouRlsBchNum" : 0,
  "VouRlsInvCode" : "string",
  "VouRlsNum" : 0,
  "VouFiscalCode" : "string",
  "VouTax3Code" : "string",
  "VouTax4Code" : "string",
  "VouTax5Code" : "string",
  "VouInvSeriesCode" : "string",
  "VouShplCode" : "string",
  "VouPoPickFlag" : "string",
  "VouTax3DiscCode" : "string",
  "VouTax4DiscCode" : "string",
  "VouTax5DiscCode" : "string",
  "VouTax1DirectFlag" : "string",
  "VouTax2DirectFlag" : "string",
  "VouTax3DirectFlag" : "string",
  "VouTax4DirectFlag" : "string",
  "VouTax5DirectFlag" : "string",
  "VouTax1IncFlag" : "string",
  "VouTax2IncFlag" : "string",
  "VouTax3IncFlag" : "string",
  "VouTax4IncFlag" : "string",
  "VouTax5IncFlag" : "string",
  "VouTax1CreditFlag" : "string",
  "VouTax2CreditFlag" : "string",
  "VouTax3CreditFlag" : "string",
  "VouTax4CreditFlag" : "string",
  "VouTax5CreditFlag" : "string",
  "VouOperationCode" : "string",
  "VouDfttaxFromCode" : "string",
  "VouChqHandleCode" : "string",
  "VouDiscreteChqFlag" : "string",
  "VouRemitDesc" : "string",
  "Vou1099Code" : "string",
  "VouTax2HldbkCode" : "string",
  "VouPoReleaseNum" : 0,
  "VouSubcontrCode" : "string",
  "VouRevDate" : "YYYY-MM-dd or YYYY-MM-ddTHH:mm:ss-ZZ:ZZ",
  "VouRevBchNum" : 0,
  "VouDrawNum" : 0,
  "VouRlsDate" : "YYYY-MM-dd or YYYY-MM-ddTHH:mm:ss-ZZ:ZZ",
  "VouValuateFromDate" : "YYYY-MM-dd or YYYY-MM-ddTHH:mm:ss-ZZ:ZZ",
  "VouValuateToDate" : "YYYY-MM-dd or YYYY-MM-ddTHH:mm:ss-ZZ:ZZ",
  "VouVendorInvCode" : "string",
  "VouMultiControlJobFlag" : "string",
  "VouPayNotes" : "string",
  "VouRegInvNum" : 0,
  "VouImageFilename" : "string",
  "VouVenAddCode" : "string",
  "VouScApplyBchNum" : 0,
  "VouHoldFlag" : "string",
  "VouJobCompCode" : "string",
  "VouRlsTax1Code" : "string",
  "VouRlsTax2Code" : "string",
  "VouScModifiedFlag" : "string",
  "VouScApprovedFlag" : "string",
  "VouPayByManualChqFlag" : "string",
  "VouChqPayeeName" : "string",
  "VouNonZeroOweCompVenCode" : "string",
  "VouExpDeptCode" : "string",
  "VouSelForVoidFlag" : "string",
  "VouEftFlag" : "string",
  "VouTax1TaxableFlag" : "string",
  "VouTax2TaxableFlag" : "string",
  "VouTax3TaxableFlag" : "string",
  "VouTax4TaxableFlag" : "string",
  "VouTax5TaxableFlag" : "string",
  "VouRecordStatus" : "string",
  "VouPartnCode" : "string",
  "VouPartnTypeCode" : "string",
  "VouContactCode" : "string",
  "VouHoldPaymentFlag" : "string",
  "VouHoldPaymentDays" : 0,
  "VouOriginatingVouNum" : 0,
  "VouSplitByApplCode" : "string",
  "VouScmstJobCode" : "string",
  "VouDuplicateId" : "string",
  "VouContExceedHoldFlag" : "string",
  "VouUnpostedPayCodeOverride" : "string",
  "VouRevisionNum" : 0,
  "VouSeparateBillingRefCode" : "string",
  "VouCreatedByJbFlag" : "string",
  "VouSourceTypeCode" : "string",
  "VouSourceFromDate" : "YYYY-MM-dd or YYYY-MM-ddTHH:mm:ss-ZZ:ZZ",
  "VouSourceToDate" : "YYYY-MM-dd or YYYY-MM-ddTHH:mm:ss-ZZ:ZZ",
  "VouUnpostedRfpInfo" : "string",
  "VouPyTaxVoucherFlag" : "string",
  "VouPrelienComplPayCode" : "string",
  "VouOrigBchNum" : 0,
  "VouAppr1" : "string",
  "VouAppr2" : "string",
  "VouRoutJob" : "string",
  "VouTppayCode" : "string",
  "VouScSelfBilledFlag" : "string",
  "VouFinalRfpFlag" : "string",
  "VouTpPaymodeTypeCode" : "string",
  "VouDistTypeCode" : "string",
  "VouCostCode" : "string",
  "VouCatCode" : "string",
  "VouDeptAcct" : "string",
  "VouInvHldbkTaxFlag" : "string",
  "VouImportingGoodsFlag" : "string",
  "VouDeptCodeDist" : "string",
  "VouPyIrsTaxType" : "string",
  "VouPyIrsTaxInfoId" : "string",
  "VouPyIrsTaxPerEndDate" : "YYYY-MM-dd or YYYY-MM-ddTHH:mm:ss-ZZ:ZZ",
  "VouDiscAllocMethCode" : "string",
  "VouLastSessioninfo" : "string",
  "VouBchrgInvFlag" : "string",
  "VouResaleInfo" : "string",
  "VouImportInfo" : "string",
  "VouNatureOfServices" : "string",
  "VouContractorPrelimFlag" : "string",
  "VouMaterialInvFlag" : "string",
  "VouCreatedByManchqFlag" : "string",
  "VouAcctDescription" : "string",
  "VouAuxData" : "string",
  "VouWorkflowStatus" : "string"
}</con:sampleContent>
    </con:representation>
    <con:representation type="RESPONSE">
      <con:mediaType>application/json</con:mediaType>
      <con:status>400</con:status>
      <con:params/>
      <con:description>An error occurred while attempting to retrieve, create, or delete record(s)</con:description>
    </con:representation>
    <con:request name="Request 1" id="a0203042-0c7e-43bb-b419-6bfe0cc06218" mediaType="application/json">
      <con:settings/>
      <con:endpoint>https://mobtest.cmiccloudr12.com/cmictestrti</con:endpoint>
      <con:request/>
      <con:credentials>
        <con:selectedAuthProfile>No Authorization</con:selectedAuthProfile>
        <con:authType>No Authorization</con:authType>
      </con:credentials>
      <con:parameters>
        <con:entry key="WorkflowStatusVar" value=""/>
        <con:entry key="finder" value=""/>
      </con:parameters>
    </con:request>
  </con:method>
</con:resource>
