<?xml version="1.0" encoding="UTF-8"?>
<con:resource name="/hcm-rest-api/rest/1/pyemphourtype/{Vuuid}" path="/hcm-rest-api/rest/1/pyemphourtype/{Vuuid}" id="53751fb3-8988-4a68-928a-9980a6ebe629" xmlns:con="http://eviware.com/soapui/config">
  <con:settings>
    <con:setting id="53751fb3-8988-4a68-928a-9980a6ebe629fileName">%2Fhcm-rest-api%2Frest%2F1%2Fpyemphourtype%2F%7BVuuid%7D</con:setting>
  </con:settings>
  <con:parameters/>
  <con:method name="GET" id="7cc347db-17f7-4ffa-a4a3-a5c3be4d2d30" method="GET">
    <con:description>Retrieve a Specific PY Employee Hour Type</con:description>
    <con:settings/>
    <con:parameters>
      <con:parameter required="true">
        <con:name>Vuuid</con:name>
        <con:style>TEMPLATE</con:style>
        <con:description>Unique ID of Row</con:description>
      </con:parameter>
    </con:parameters>
    <con:representation type="RESPONSE">
      <con:mediaType>application/json</con:mediaType>
      <con:status>200</con:status>
      <con:params/>
      <con:description>Successful Operation</con:description>
      <con:sampleContent>{
  "EhourEmpNo" : "string",
  "EhourCompCode" : "string",
  "EhourHourCode" : "string",
  "EhourVUuid" : "string",
  "EhourIuCreateDate" : "YYYY-MM-dd or YYYY-MM-ddTHH:mm:ss-ZZ:ZZ",
  "EhourIuCreateUser" : "string",
  "EhourIuUpdateDate" : "YYYY-MM-dd or YYYY-MM-ddTHH:mm:ss-ZZ:ZZ",
  "EhourIuUpdateUser" : "string"
}</con:sampleContent>
    </con:representation>
    <con:representation type="RESPONSE">
      <con:mediaType>application/json</con:mediaType>
      <con:status>400</con:status>
      <con:params/>
      <con:description>An error occurred while attempting to retrieve, create, or delete record(s)</con:description>
    </con:representation>
    <con:request name="Request 1" id="77096d98-d3ee-40ab-9c4d-564b24e80958" mediaType="application/json">
      <con:settings/>
      <con:endpoint>https://mobtest.cmiccloudr12.com/cmictestrti</con:endpoint>
      <con:parameters/>
    </con:request>
  </con:method>
  <con:method name="DELETE" id="05ca344a-dabf-4133-8676-64cbe1b38f47" method="DELETE">
    <con:description>Delete a Specific PY Employee Hour Type</con:description>
    <con:settings/>
    <con:parameters>
      <con:parameter required="true">
        <con:name>Vuuid</con:name>
        <con:style>TEMPLATE</con:style>
        <con:description>Unique Row ID</con:description>
      </con:parameter>
    </con:parameters>
    <con:representation type="RESPONSE">
      <con:mediaType>application/json</con:mediaType>
      <con:status>204</con:status>
      <con:params/>
      <con:description>Object has been successfully deleted.</con:description>
    </con:representation>
    <con:representation type="RESPONSE">
      <con:mediaType>application/json</con:mediaType>
      <con:status>400</con:status>
      <con:params/>
      <con:description>An error occurred while attempting to retrieve, create, or delete record(s)</con:description>
    </con:representation>
    <con:request name="Request 1" id="ba1fac6f-aeed-48f6-9caa-d6a588917f61" mediaType="application/json">
      <con:settings/>
      <con:endpoint>https://mobtest.cmiccloudr12.com/cmictestrti</con:endpoint>
      <con:parameters/>
    </con:request>
  </con:method>
</con:resource>
