<?xml version="1.0" encoding="UTF-8"?>
<con:resource name="/prm-rest-api/rest/1/prmworkorder/{Vuuid}" path="/prm-rest-api/rest/1/prmworkorder/{Vuuid}" id="e81bba0f-4ec7-46df-989d-742409ca0280" xmlns:con="http://eviware.com/soapui/config" xmlns:xsi="http://www.w3.org/2001/XMLSchema-instance">
  <con:settings>
    <con:setting id="e81bba0f-4ec7-46df-989d-742409ca0280fileName">%2Fprm-rest-api%2Frest%2F1%2Fprmworkorder%2F%7BVuuid%7D</con:setting>
  </con:settings>
  <con:parameters/>
  <con:method name="GET" id="db8d9503-737e-45ca-a802-0aedef08b394" method="GET">
    <con:description>Retrieve a Specific PRM work order</con:description>
    <con:settings/>
    <con:parameters>
      <con:parameter required="true">
        <con:name>Vuuid</con:name>
        <con:value/>
        <con:style>TEMPLATE</con:style>
        <con:default/>
        <con:description>Unique Row ID</con:description>
      </con:parameter>
    </con:parameters>
    <con:representation type="RESPONSE">
      <con:mediaType>application/json</con:mediaType>
      <con:status>200</con:status>
      <con:params/>
      <con:description>Successful Operation</con:description>
      <con:sampleContent>{
  "WoCompCode" : "string",
  "WoCompName" : "string",
  "WoCode" : "string",
  "WoNumber" : 0,
  "WoDescription" : "string",
  "WoType" : "string",
  "WoCostingType" : "string",
  "WoBillingType" : "string",
  "WoStatus" : "string",
  "WoShopWoFlag" : "string",
  "WoReceivedDateTime" : "YYYY-MM-dd or YYYY-MM-ddTHH:mm:ss-ZZ:ZZ",
  "WoReqStartDateTime" : "YYYY-MM-dd or YYYY-MM-ddTHH:mm:ss-ZZ:ZZ",
  "WoReqEndDateTime" : "YYYY-MM-dd or YYYY-MM-ddTHH:mm:ss-ZZ:ZZ",
  "WoDispatchedDateTime" : "YYYY-MM-dd or YYYY-MM-ddTHH:mm:ss-ZZ:ZZ",
  "WoStartDateTime" : "YYYY-MM-dd or YYYY-MM-ddTHH:mm:ss-ZZ:ZZ",
  "WoCompletionDateTime" : "YYYY-MM-dd or YYYY-MM-ddTHH:mm:ss-ZZ:ZZ",
  "WoComments" : "string",
  "WoClass1" : "string",
  "WoClass2" : "string",
  "WoClass3" : "string",
  "WoClass4" : "string",
  "WoPrintCounter" : 0,
  "WoMteamCode" : "string",
  "WoCreatedBy" : "string",
  "WoDateCreated" : "YYYY-MM-dd or YYYY-MM-ddTHH:mm:ss-ZZ:ZZ",
  "WoModifiedBy" : "string",
  "WoDateModified" : "YYYY-MM-dd or YYYY-MM-ddTHH:mm:ss-ZZ:ZZ",
  "WoTranType" : "string",
  "WoCostCompCode" : "string",
  "WoCostCompName" : "string",
  "WoCostDeptCode" : "string",
  "WoCostDeptName" : "string",
  "WoVendorCode" : "string",
  "WoTitle" : "string",
  "WoDeptCode" : "string",
  "WoDeptName" : "string",
  "WoCostJobCode" : "string",
  "WoCostJobName" : "string",
  "WoCustCode" : "string",
  "WoCustName" : "string",
  "WoAppTypeCode" : "string",
  "WoIssueId" : "string",
  "WoDmLocCode" : "string",
  "WoBillingRateTableCode" : "string",
  "WoInvoiceFormat" : "string",
  "WoClvValueCode1" : "string",
  "WoClvValueCode2" : "string",
  "WoClvValueCode3" : "string",
  "WoClvValueCode4" : "string",
  "WoClvValueCode5" : "string",
  "WoClvValueCode6" : "string",
  "WoEntry2Flag" : "string",
  "WoUserField1" : "string",
  "WoReceivedTimeHh" : "string",
  "WoReceivedTimeMi" : "string",
  "WoReceivedTimeAmPm" : "string",
  "WoIuCreateDate" : "YYYY-MM-dd or YYYY-MM-ddTHH:mm:ss-ZZ:ZZ",
  "WoIuCreateUser" : "string",
  "WoIuUpdateDate" : "YYYY-MM-dd or YYYY-MM-ddTHH:mm:ss-ZZ:ZZ",
  "WoIuUpdateUser" : "string",
  "WoVUuid" : "string",
  "WoEqpCode" : "string"
}</con:sampleContent>
    </con:representation>
    <con:representation type="RESPONSE">
      <con:mediaType>application/json</con:mediaType>
      <con:status>400</con:status>
      <con:params/>
      <con:description>An error occurred while attempting to retrieve, create, or delete record(s)</con:description>
    </con:representation>
    <con:request name="Request 1" id="03bd0125-f400-460c-b9c1-9902f649b099" mediaType="application/json">
      <con:settings/>
      <con:endpoint>https://mobtest.cmiccloudr12.com/cmictestrti</con:endpoint>
      <con:request/>
      <con:credentials>
        <con:selectedAuthProfile>No Authorization</con:selectedAuthProfile>
        <con:authType>No Authorization</con:authType>
      </con:credentials>
      <con:parameters>
        <con:entry key="Vuuid" value=""/>
      </con:parameters>
    </con:request>
  </con:method>
  <con:method name="PATCH" id="db986702-e327-4b75-bb74-b629205dbaad" method="PATCH">
    <con:description>Update a Specific PRM work order</con:description>
    <con:settings/>
    <con:parameters>
      <con:parameter required="true">
        <con:name>Vuuid</con:name>
        <con:value/>
        <con:style>TEMPLATE</con:style>
        <con:default/>
        <con:description>Unique Row ID</con:description>
      </con:parameter>
    </con:parameters>
    <con:representation type="RESPONSE">
      <con:mediaType>application/json</con:mediaType>
      <con:status>200</con:status>
      <con:params/>
      <con:description>Successful Operation</con:description>
      <con:sampleContent>{
  "WoCompCode" : "string",
  "WoCompName" : "string",
  "WoCode" : "string",
  "WoNumber" : 0,
  "WoDescription" : "string",
  "WoType" : "string",
  "WoCostingType" : "string",
  "WoBillingType" : "string",
  "WoStatus" : "string",
  "WoShopWoFlag" : "string",
  "WoReceivedDateTime" : "YYYY-MM-dd or YYYY-MM-ddTHH:mm:ss-ZZ:ZZ",
  "WoReqStartDateTime" : "YYYY-MM-dd or YYYY-MM-ddTHH:mm:ss-ZZ:ZZ",
  "WoReqEndDateTime" : "YYYY-MM-dd or YYYY-MM-ddTHH:mm:ss-ZZ:ZZ",
  "WoDispatchedDateTime" : "YYYY-MM-dd or YYYY-MM-ddTHH:mm:ss-ZZ:ZZ",
  "WoStartDateTime" : "YYYY-MM-dd or YYYY-MM-ddTHH:mm:ss-ZZ:ZZ",
  "WoCompletionDateTime" : "YYYY-MM-dd or YYYY-MM-ddTHH:mm:ss-ZZ:ZZ",
  "WoComments" : "string",
  "WoClass1" : "string",
  "WoClass2" : "string",
  "WoClass3" : "string",
  "WoClass4" : "string",
  "WoPrintCounter" : 0,
  "WoMteamCode" : "string",
  "WoCreatedBy" : "string",
  "WoDateCreated" : "YYYY-MM-dd or YYYY-MM-ddTHH:mm:ss-ZZ:ZZ",
  "WoModifiedBy" : "string",
  "WoDateModified" : "YYYY-MM-dd or YYYY-MM-ddTHH:mm:ss-ZZ:ZZ",
  "WoTranType" : "string",
  "WoCostCompCode" : "string",
  "WoCostCompName" : "string",
  "WoCostDeptCode" : "string",
  "WoCostDeptName" : "string",
  "WoVendorCode" : "string",
  "WoTitle" : "string",
  "WoDeptCode" : "string",
  "WoDeptName" : "string",
  "WoCostJobCode" : "string",
  "WoCostJobName" : "string",
  "WoCustCode" : "string",
  "WoCustName" : "string",
  "WoAppTypeCode" : "string",
  "WoIssueId" : "string",
  "WoDmLocCode" : "string",
  "WoBillingRateTableCode" : "string",
  "WoInvoiceFormat" : "string",
  "WoClvValueCode1" : "string",
  "WoClvValueCode2" : "string",
  "WoClvValueCode3" : "string",
  "WoClvValueCode4" : "string",
  "WoClvValueCode5" : "string",
  "WoClvValueCode6" : "string",
  "WoEntry2Flag" : "string",
  "WoUserField1" : "string",
  "WoReceivedTimeHh" : "string",
  "WoReceivedTimeMi" : "string",
  "WoReceivedTimeAmPm" : "string",
  "WoIuCreateDate" : "YYYY-MM-dd or YYYY-MM-ddTHH:mm:ss-ZZ:ZZ",
  "WoIuCreateUser" : "string",
  "WoIuUpdateDate" : "YYYY-MM-dd or YYYY-MM-ddTHH:mm:ss-ZZ:ZZ",
  "WoIuUpdateUser" : "string",
  "WoVUuid" : "string",
  "WoEqpCode" : "string"
}</con:sampleContent>
    </con:representation>
    <con:representation type="RESPONSE">
      <con:mediaType>application/json</con:mediaType>
      <con:status>400</con:status>
      <con:params/>
      <con:description>An error occurred while attempting to retrieve, create, or delete record(s)</con:description>
    </con:representation>
    <con:representation type="REQUEST">
      <con:mediaType>application/vnd.oracle.adf.resourceitem+json</con:mediaType>
      <con:params/>
      <con:sampleContent>{"WoReceivedDateTime":"string","WoType":"string","WoTranType":"G","WoStatus":"string","WoCompCode":"string","WoCostCompCode":"string","WoCostDeptCode":"string","WoCode":"string","WoNumber":"integer","WoCostingType":"string","WoPrintCounter":"integer","WoPriorityNumber":"integer","WoBillingType":"string"}</con:sampleContent>
    </con:representation>
    <con:representation type="REQUEST">
      <con:mediaType>application/vnd.oracle.adf.batch+json</con:mediaType>
      <con:params/>
      <con:sampleContent>{"parts":[{"id":"part1","path":"/1/prmworkorder","operation":"create","payload":{"WoReceivedDateTime":"2022-11-01","WoType":"C","WoTranType":"G","WoStatus":"S","WoCompCode":"ZZ","WoCostCompCode":"ZZ","WoCostDeptCode":"00","WoCode":"ROSHAN19","WoNumber":"7","WoCostingType":"N","WoPrintCounter":"0","WoPriorityNumber":"3","WoBillingType":"N","PrmWorkItemViewObj":[{"WitmWoStepTitle":"okay 3 boss","WitmWoStepDescription":"stop everything","WitmPriority":4,"WitmWorkItemType":"JB","WitmAppTypeCode":"CRM","WitmBillingType":"F","WitmStatus":"O","WitmMissedTaskCount":"0","WitmRecurringFlag":"0","WitmDeadlineDate":"2022-11-01","WitmThresholdDate":"2022-11-01"},{"WitmWoStepTitle":"okay for me - not for you","WitmWoStepDescription":"i'm here to test a new life","WitmPriority":3,"WitmWorkItemType":"JB","WitmAppTypeCode":"CRM","WitmBillingType":"F","WitmStatus":"O","WitmMissedTaskCount":"0","WitmRecurringFlag":"0","WitmDeadlineDate":"2022-11-02","WitmThresholdDate":"2022-11-02"}]}},{"id":"part2","path":"/1/prmworkorder","operation":"create","payload":{"WoReceivedDateTime":"2022-11-01","WoType":"C","WoTranType":"G","WoStatus":"S","WoCompCode":"ZZ","WoCostCompCode":"ZZ","WoCostDeptCode":"00","WoCode":"ROSHAN20","WoNumber":"7","WoCostingType":"N","WoPrintCounter":"0","WoPriorityNumber":"3","WoBillingType":"N","PrmWorkItemViewObj":[{"WitmWoStepTitle":"okay 3 boss","WitmWoStepDescription":"stop everything","WitmPriority":4,"WitmWorkItemType":"JB","WitmAppTypeCode":"CRM","WitmBillingType":"F","WitmStatus":"O","WitmMissedTaskCount":"0","WitmRecurringFlag":"0","WitmDeadlineDate":"2022-11-01","WitmThresholdDate":"2022-11-01"},{"WitmWoStepTitle":"okay for me - not for you","WitmWoStepDescription":"i'm here to test a new life","WitmPriority":3,"WitmWorkItemType":"JB","WitmAppTypeCode":"CRM","WitmBillingType":"F","WitmStatus":"O","WitmMissedTaskCount":"0","WitmRecurringFlag":"0","WitmDeadlineDate":"2022-11-02","WitmThresholdDate":"2022-11-02"}]}}]}</con:sampleContent>
    </con:representation>
    <con:request name="G-Type Example" id="64262525-ef55-46a8-9734-f1625d1d11d7" mediaType="application/vnd.oracle.adf.resourceitem+json">
      <con:settings/>
      <con:endpoint>https://mobtest.cmiccloudr12.com/cmictestrti</con:endpoint>
      <con:request>{"WoReceivedDateTime":"string","WoType":"string","WoTranType":"G","WoStatus":"string","WoCompCode":"string","WoCostCompCode":"string","WoCostDeptCode":"string","WoCode":"string","WoNumber":"integer","WoCostingType":"string","WoPrintCounter":"integer","WoPriorityNumber":"integer","WoBillingType":"string"}</con:request>
      <con:credentials>
        <con:selectedAuthProfile>No Authorization</con:selectedAuthProfile>
        <con:authType>No Authorization</con:authType>
      </con:credentials>
      <con:parameters>
        <con:entry key="Vuuid" value=""/>
      </con:parameters>
    </con:request>
    <con:request name="J-Type Example" id="9e2ebe7c-8b55-4cd4-8fd8-61b48f0c9971" mediaType="application/vnd.oracle.adf.resourceitem+json">
      <con:settings/>
      <con:endpoint>https://mobtest.cmiccloudr12.com/cmictestrti</con:endpoint>
      <con:request>{"WoReceivedDateTime":"string","WoType":"string","WoTranType":"J","WoStatus":"string","WoCompCode":"string","WoCostCompCode":"string","WoCostJobCode":"string","WoCode":"string","WoNumber":"integer","WoCostingType":"string","WoPrintCounter":"integer","WoPriorityNumber":"integer","WoBillingType":"string"}</con:request>
      <con:credentials>
        <con:selectedAuthProfile>No Authorization</con:selectedAuthProfile>
        <con:authType>No Authorization</con:authType>
      </con:credentials>
      <con:parameters>
        <con:entry key="Vuuid" value=""/>
      </con:parameters>
    </con:request>
    <con:request name="E-Type Example" id="298caf99-ee41-43dc-abe8-37a41dcc77ca" mediaType="application/vnd.oracle.adf.resourceitem+json">
      <con:settings/>
      <con:endpoint>https://mobtest.cmiccloudr12.com/cmictestrti</con:endpoint>
      <con:request>{"WoReceivedDateTime":"string","WoType":"string","WoTranType":"E","WoStatus":"string","WoCompCode":"string","WoCostCompCode":"string","WoEqpCode":"string","WoCode":"string","WoNumber":"integer","WoCostingType":"string","WoPrintCounter":"integer","WoPriorityNumber":"integer","WoBillingType":"string"}</con:request>
      <con:credentials>
        <con:selectedAuthProfile>No Authorization</con:selectedAuthProfile>
        <con:authType>No Authorization</con:authType>
      </con:credentials>
      <con:parameters>
        <con:entry key="Vuuid" value=""/>
      </con:parameters>
    </con:request>
    <con:request name="Work Order with Work Item Example" id="a3313c49-c018-4f4e-9123-19bbea464ee1" mediaType="application/vnd.oracle.adf.resourceitem+json">
      <con:settings/>
      <con:endpoint>https://mobtest.cmiccloudr12.com/cmictestrti</con:endpoint>
      <con:request>{"WoReceivedDateTime":"2022-11-01","WoType":"C","WoTranType":"G","WoStatus":"S","WoCompCode":"ZZ","WoCostCompCode":"ZZ","WoCostDeptCode":"00","WoCode":"ROSHAN30","WoNumber":"7","WoCostingType":"N","WoPrintCounter":"0","WoPriorityNumber":"3","WoBillingType":"N","PrmWorkItemViewObj":[{"WitmWoStepTitle":"i'm so lost","WitmWoStepDescription":"keep going bro","WitmPriority":2,"WitmWorkItemType":"JB","WitmAppTypeCode":"CRM","WitmBillingType":"F","WitmStatus":"O","WitmMissedTaskCount":"0","WitmRecurringFlag":"0","WitmDeadlineDate":"2022-11-02","WitmThresholdDate":"2022-11-02"}]}</con:request>
      <con:credentials>
        <con:selectedAuthProfile>No Authorization</con:selectedAuthProfile>
        <con:authType>No Authorization</con:authType>
      </con:credentials>
      <con:parameters>
        <con:entry key="Vuuid" value=""/>
      </con:parameters>
    </con:request>
    <con:request name="Work Order with Multiple Work Items Example" id="fedf1820-7b68-4fe9-8c09-48437d3d3ce0" mediaType="application/vnd.oracle.adf.resourceitem+json">
      <con:settings/>
      <con:endpoint>https://mobtest.cmiccloudr12.com/cmictestrti</con:endpoint>
      <con:request>{"WoReceivedDateTime":"2022-11-01","WoType":"C","WoTranType":"G","WoStatus":"S","WoCompCode":"ZZ","WoCostCompCode":"ZZ","WoCostDeptCode":"00","WoCode":"ROSHAN21","WoNumber":"7","WoCostingType":"N","WoPrintCounter":"0","WoPriorityNumber":"3","WoBillingType":"N","PrmWorkItemViewObj":[{"WitmWoStepTitle":"okay 3 boss","WitmWoStepDescription":"stop everything","WitmPriority":4,"WitmWorkItemType":"JB","WitmAppTypeCode":"CRM","WitmBillingType":"F","WitmStatus":"O","WitmMissedTaskCount":"0","WitmRecurringFlag":"0","WitmDeadlineDate":"2022-11-01","WitmThresholdDate":"2022-11-01"},{"WitmWoStepTitle":"okay for me - not for you","WitmWoStepDescription":"i'm here to test a new life","WitmPriority":3,"WitmWorkItemType":"JB","WitmAppTypeCode":"CRM","WitmBillingType":"F","WitmStatus":"O","WitmMissedTaskCount":"0","WitmRecurringFlag":"0","WitmDeadlineDate":"2022-11-02","WitmThresholdDate":"2022-11-02"}]}</con:request>
      <con:credentials>
        <con:selectedAuthProfile>No Authorization</con:selectedAuthProfile>
        <con:authType>No Authorization</con:authType>
      </con:credentials>
      <con:parameters>
        <con:entry key="Vuuid" value=""/>
      </con:parameters>
    </con:request>
    <con:request name="Patch Example" id="4c27c65a-1146-40c2-9500-44f8b2c09514" mediaType="application/vnd.oracle.adf.resourceitem+json">
      <con:settings/>
      <con:endpoint>https://mobtest.cmiccloudr12.com/cmictestrti</con:endpoint>
      <con:request>{"WoDescription":"bobicus was here"}</con:request>
      <con:credentials>
        <con:selectedAuthProfile>No Authorization</con:selectedAuthProfile>
        <con:authType>No Authorization</con:authType>
      </con:credentials>
      <con:parameters>
        <con:entry key="Vuuid" value=""/>
      </con:parameters>
    </con:request>
    <con:request name="Multiple Work orders with Work Items Example" id="6b916f9f-c0ee-4818-a16c-eef56d0d038b" mediaType="application/vnd.oracle.adf.batch+json">
      <con:settings/>
      <con:endpoint>https://mobtest.cmiccloudr12.com/cmictestrti</con:endpoint>
      <con:request>{"parts":[{"id":"part1","path":"/1/prmworkorder","operation":"create","payload":{"WoReceivedDateTime":"2022-11-01","WoType":"C","WoTranType":"G","WoStatus":"S","WoCompCode":"ZZ","WoCostCompCode":"ZZ","WoCostDeptCode":"00","WoCode":"ROSHAN19","WoNumber":"7","WoCostingType":"N","WoPrintCounter":"0","WoPriorityNumber":"3","WoBillingType":"N","PrmWorkItemViewObj":[{"WitmWoStepTitle":"okay 3 boss","WitmWoStepDescription":"stop everything","WitmPriority":4,"WitmWorkItemType":"JB","WitmAppTypeCode":"CRM","WitmBillingType":"F","WitmStatus":"O","WitmMissedTaskCount":"0","WitmRecurringFlag":"0","WitmDeadlineDate":"2022-11-01","WitmThresholdDate":"2022-11-01"},{"WitmWoStepTitle":"okay for me - not for you","WitmWoStepDescription":"i'm here to test a new life","WitmPriority":3,"WitmWorkItemType":"JB","WitmAppTypeCode":"CRM","WitmBillingType":"F","WitmStatus":"O","WitmMissedTaskCount":"0","WitmRecurringFlag":"0","WitmDeadlineDate":"2022-11-02","WitmThresholdDate":"2022-11-02"}]}},{"id":"part2","path":"/1/prmworkorder","operation":"create","payload":{"WoReceivedDateTime":"2022-11-01","WoType":"C","WoTranType":"G","WoStatus":"S","WoCompCode":"ZZ","WoCostCompCode":"ZZ","WoCostDeptCode":"00","WoCode":"ROSHAN20","WoNumber":"7","WoCostingType":"N","WoPrintCounter":"0","WoPriorityNumber":"3","WoBillingType":"N","PrmWorkItemViewObj":[{"WitmWoStepTitle":"okay 3 boss","WitmWoStepDescription":"stop everything","WitmPriority":4,"WitmWorkItemType":"JB","WitmAppTypeCode":"CRM","WitmBillingType":"F","WitmStatus":"O","WitmMissedTaskCount":"0","WitmRecurringFlag":"0","WitmDeadlineDate":"2022-11-01","WitmThresholdDate":"2022-11-01"},{"WitmWoStepTitle":"okay for me - not for you","WitmWoStepDescription":"i'm here to test a new life","WitmPriority":3,"WitmWorkItemType":"JB","WitmAppTypeCode":"CRM","WitmBillingType":"F","WitmStatus":"O","WitmMissedTaskCount":"0","WitmRecurringFlag":"0","WitmDeadlineDate":"2022-11-02","WitmThresholdDate":"2022-11-02"}]}}]}</con:request>
      <con:credentials>
        <con:selectedAuthProfile>No Authorization</con:selectedAuthProfile>
        <con:authType>No Authorization</con:authType>
      </con:credentials>
      <con:parameters>
        <con:entry key="Vuuid" value=""/>
      </con:parameters>
    </con:request>
  </con:method>
</con:resource>
